dictToHtml/__init__.py
dictToHtml/core.py
docs/image.png
dicttohtml-0.1.3.dist-info/METADATA
dicttohtml-0.1.3.dist-info/WHEEL
dicttohtml-0.1.3.dist-info/RECORD
