Metadata-Version: 2.1
Name: dicttohtml
Version: 0.1.3
Summary: dictToHtml是一个强大的Python工具，用于将Python字典转换为功能基本的HTML页面。它提供了一种简单直观的方式来通过字典配置生成包含各种UI组件和交互功能的网页
Home-page: https://github.com/xiwen-haochi/dictTohtml
License: MIT
Keywords: dict to html,html,dict
Author: 'fkl'
Author-email: 18654198191@163.com
Requires-Python: >=3.6,<4.0
Classifier: License :: OSI Approved :: MIT License
Classifier: Programming Language :: Python :: 3
Classifier: Programming Language :: Python :: 3.6
Classifier: Programming Language :: Python :: 3.7
Classifier: Programming Language :: Python :: 3.8
Classifier: Programming Language :: Python :: 3.9
Classifier: Programming Language :: Python :: 3.10
Classifier: Programming Language :: Python :: 3.11
Classifier: Programming Language :: Python :: 3.12
Classifier: Programming Language :: Python :: 3.13
Project-URL: Repository, https://github.com/xiwen-haochi/dictTohtml
